<?xml version="1.0"?>
<?iotk version="1.2.0"?>
<?iotk file_version="1.0"?>
<?iotk binary="F"?>
<?iotk qe_syntax="F"?>
<Root>
  <GEOMETRY_INFO>
    <NUMBER_OF_TYPES type="integer" size="1">
         2
    </NUMBER_OF_TYPES>
    <NUMBER_OF_ATOMS type="integer" size="1">
         2
    </NUMBER_OF_ATOMS>
    <BRAVAIS_LATTICE_INDEX type="integer" size="1">
         2
    </BRAVAIS_LATTICE_INDEX>
    <SPIN_COMPONENTS type="integer" size="1">
         1
    </SPIN_COMPONENTS>
    <CELL_DIMENSIONS type="real" size="6">
 1.050000000000000E+001
 0.000000000000000E+000
 0.000000000000000E+000
 0.000000000000000E+000
 0.000000000000000E+000
 0.000000000000000E+000
    </CELL_DIMENSIONS>
    <AT type="real" size="9" columns="3">
-5.000000000000000E-001  0.000000000000000E+000  5.000000000000000E-001 
 0.000000000000000E+000  5.000000000000000E-001  5.000000000000000E-001 
-5.000000000000000E-001  5.000000000000000E-001  0.000000000000000E+000
    </AT>
    <BG type="real" size="9" columns="3">
-1.000000000000000E+000 -1.000000000000000E+000  1.000000000000000E+000 
 1.000000000000000E+000  1.000000000000000E+000  1.000000000000000E+000 
-1.000000000000000E+000  1.000000000000000E+000 -1.000000000000000E+000
    </BG>
    <UNIT_CELL_VOLUME_AU type="real" size="1">
 2.894062500000000E+002
    </UNIT_CELL_VOLUME_AU>
    <TYPE_NAME.1 type="character" size="1" len="3">
Al 
    </TYPE_NAME.1>
    <MASS.1 type="real" size="1">
 2.698000000000000E+001
    </MASS.1>
    <TYPE_NAME.2 type="character" size="1" len="3">
As 
    </TYPE_NAME.2>
    <MASS.2 type="real" size="1">
 7.492000000000000E+001
    </MASS.2>
    <ATOM.1 SPECIES="Al " INDEX="1" TAU="0.000000000000000E+000 0.000000000000000E+000 0.000000000000000E+000"/>
    <ATOM.2 SPECIES="As " INDEX="2" TAU="2.500000000000000E-001 2.500000000000000E-001 2.500000000000000E-001"/>
    <NUMBER_OF_Q type="integer" size="1">
         4
    </NUMBER_OF_Q>
  </GEOMETRY_INFO>
  <DYNAMICAL_MAT_.1>
    <Q_POINT type="real" size="3" columns="3">
 5.000000000000000E-001 -5.000000000000000E-001  5.000000000000000E-001
    </Q_POINT>
    <PHI.1.1 type="complex" size="9">
 2.369984040402063E-001, 0.000000000000000E+000
-3.075739158505794E-002, 0.000000000000000E+000
 3.075739158505789E-002, 0.000000000000000E+000
-3.075739158505794E-002, 0.000000000000000E+000
 2.369984040402063E-001, 0.000000000000000E+000
-3.075739158505791E-002, 0.000000000000000E+000
 3.075739158505789E-002, 0.000000000000000E+000
-3.075739158505794E-002, 0.000000000000000E+000
 2.369984040402063E-001, 0.000000000000000E+000
    </PHI.1.1>
    <PHI.1.2 type="complex" size="9">
-1.093193310824842E-001, 0.000000000000000E+000
-8.030721305131815E-002, 0.000000000000000E+000
 8.030721305131817E-002, 0.000000000000000E+000
-8.030721305131815E-002, 0.000000000000000E+000
-1.093193310824842E-001, 0.000000000000000E+000
-8.030721305131817E-002, 0.000000000000000E+000
 8.030721305131817E-002, 0.000000000000000E+000
-8.030721305131815E-002, 0.000000000000000E+000
-1.093193310824842E-001, 0.000000000000000E+000
    </PHI.1.2>
    <PHI.2.1 type="complex" size="9">
-1.093193310824842E-001, 0.000000000000000E+000
-8.030721305131817E-002, 0.000000000000000E+000
 8.030721305131817E-002, 0.000000000000000E+000
-8.030721305131817E-002, 0.000000000000000E+000
-1.093193310824842E-001, 0.000000000000000E+000
-8.030721305131817E-002, 0.000000000000000E+000
 8.030721305131815E-002, 0.000000000000000E+000
-8.030721305131817E-002, 0.000000000000000E+000
-1.093193310824842E-001, 0.000000000000000E+000
    </PHI.2.1>
    <PHI.2.2 type="complex" size="9">
 2.318234680748539E-001, 0.000000000000000E+000
-2.363352848976946E-002, 0.000000000000000E+000
 2.363352848976946E-002, 0.000000000000000E+000
-2.363352848976946E-002, 0.000000000000000E+000
 2.318234680748539E-001, 0.000000000000000E+000
-2.363352848976949E-002, 0.000000000000000E+000
 2.363352848976946E-002, 0.000000000000000E+000
-2.363352848976946E-002, 0.000000000000000E+000
 2.318234680748539E-001, 0.000000000000000E+000
    </PHI.2.2>
  </DYNAMICAL_MAT_.1>
  <DYNAMICAL_MAT_.2>
    <Q_POINT type="real" size="3" columns="3">
-5.000000000000000E-001 -5.000000000000000E-001 -5.000000000000000E-001
    </Q_POINT>
    <PHI.1.1 type="complex" size="9">
 2.369984040402063E-001, 0.000000000000000E+000
 3.075739158505798E-002, 0.000000000000000E+000
 3.075739158505790E-002, 0.000000000000000E+000
 3.075739158505796E-002, 0.000000000000000E+000
 2.369984040402064E-001, 0.000000000000000E+000
 3.075739158505796E-002, 0.000000000000000E+000
 3.075739158505790E-002, 0.000000000000000E+000
 3.075739158505798E-002, 0.000000000000000E+000
 2.369984040402063E-001, 0.000000000000000E+000
    </PHI.1.1>
    <PHI.1.2 type="complex" size="9">
 1.093193310824842E-001,-1.338775688950941E-017
-8.030721305131817E-002, 9.834797141174134E-018
-8.030721305131819E-002, 9.834797141174136E-018
-8.030721305131817E-002, 9.834797141174137E-018
 1.093193310824842E-001,-1.338775688950941E-017
-8.030721305131817E-002, 9.834797141174133E-018
-8.030721305131816E-002, 9.834797141174136E-018
-8.030721305131817E-002, 9.834797141174131E-018
 1.093193310824843E-001,-1.338775688950941E-017
    </PHI.1.2>
    <PHI.2.1 type="complex" size="9">
 1.093193310824843E-001, 1.338775688950941E-017
-8.030721305131816E-002,-9.834797141174134E-018
-8.030721305131819E-002,-9.834797141174133E-018
-8.030721305131819E-002,-9.834797141174134E-018
 1.093193310824842E-001, 1.338775688950941E-017
-8.030721305131819E-002,-9.834797141174133E-018
-8.030721305131819E-002,-9.834797141174139E-018
-8.030721305131816E-002,-9.834797141174134E-018
 1.093193310824842E-001, 1.338775688950941E-017
    </PHI.2.1>
    <PHI.2.2 type="complex" size="9">
 2.318234680748539E-001, 0.000000000000000E+000
 2.363352848976948E-002, 0.000000000000000E+000
 2.363352848976945E-002, 0.000000000000000E+000
 2.363352848976948E-002, 0.000000000000000E+000
 2.318234680748539E-001, 0.000000000000000E+000
 2.363352848976945E-002, 0.000000000000000E+000
 2.363352848976948E-002, 0.000000000000000E+000
 2.363352848976948E-002, 0.000000000000000E+000
 2.318234680748539E-001, 0.000000000000000E+000
    </PHI.2.2>
  </DYNAMICAL_MAT_.2>
  <DYNAMICAL_MAT_.3>
    <Q_POINT type="real" size="3" columns="3">
-5.000000000000000E-001  5.000000000000000E-001  5.000000000000000E-001
    </Q_POINT>
    <PHI.1.1 type="complex" size="9">
 2.369984040402063E-001, 0.000000000000000E+000
-3.075739158505796E-002, 0.000000000000000E+000
-3.075739158505786E-002, 0.000000000000000E+000
-3.075739158505791E-002, 0.000000000000000E+000
 2.369984040402063E-001, 0.000000000000000E+000
 3.075739158505797E-002, 0.000000000000000E+000
-3.075739158505791E-002, 0.000000000000000E+000
 3.075739158505800E-002, 0.000000000000000E+000
 2.369984040402063E-001, 0.000000000000000E+000
    </PHI.1.1>
    <PHI.1.2 type="complex" size="9">
-1.093193310824843E-001, 0.000000000000000E+000
-8.030721305131817E-002, 0.000000000000000E+000
-8.030721305131817E-002, 0.000000000000000E+000
-8.030721305131819E-002, 0.000000000000000E+000
-1.093193310824843E-001, 0.000000000000000E+000
 8.030721305131817E-002, 0.000000000000000E+000
-8.030721305131819E-002, 0.000000000000000E+000
 8.030721305131817E-002, 0.000000000000000E+000
-1.093193310824842E-001, 0.000000000000000E+000
    </PHI.1.2>
    <PHI.2.1 type="complex" size="9">
-1.093193310824842E-001, 0.000000000000000E+000
-8.030721305131815E-002, 0.000000000000000E+000
-8.030721305131817E-002, 0.000000000000000E+000
-8.030721305131815E-002, 0.000000000000000E+000
-1.093193310824842E-001, 0.000000000000000E+000
 8.030721305131817E-002, 0.000000000000000E+000
-8.030721305131817E-002, 0.000000000000000E+000
 8.030721305131817E-002, 0.000000000000000E+000
-1.093193310824843E-001, 0.000000000000000E+000
    </PHI.2.1>
    <PHI.2.2 type="complex" size="9">
 2.318234680748539E-001, 0.000000000000000E+000
-2.363352848976943E-002, 0.000000000000000E+000
-2.363352848976943E-002, 0.000000000000000E+000
-2.363352848976943E-002, 0.000000000000000E+000
 2.318234680748539E-001, 0.000000000000000E+000
 2.363352848976943E-002, 0.000000000000000E+000
-2.363352848976943E-002, 0.000000000000000E+000
 2.363352848976943E-002, 0.000000000000000E+000
 2.318234680748539E-001, 0.000000000000000E+000
    </PHI.2.2>
  </DYNAMICAL_MAT_.3>
  <DYNAMICAL_MAT_.4>
    <Q_POINT type="real" size="3" columns="3">
 5.000000000000000E-001  5.000000000000000E-001 -5.000000000000000E-001
    </Q_POINT>
    <PHI.1.1 type="complex" size="9">
 2.369984040402063E-001, 0.000000000000000E+000
 3.075739158505784E-002, 0.000000000000000E+000
-3.075739158505787E-002, 0.000000000000000E+000
 3.075739158505787E-002, 0.000000000000000E+000
 2.369984040402063E-001, 0.000000000000000E+000
-3.075739158505793E-002, 0.000000000000000E+000
-3.075739158505793E-002, 0.000000000000000E+000
-3.075739158505793E-002, 0.000000000000000E+000
 2.369984040402064E-001, 0.000000000000000E+000
    </PHI.1.1>
    <PHI.1.2 type="complex" size="9">
-1.093193310824843E-001, 0.000000000000000E+000
 8.030721305131817E-002, 0.000000000000000E+000
-8.030721305131819E-002, 0.000000000000000E+000
 8.030721305131816E-002, 0.000000000000000E+000
-1.093193310824842E-001, 0.000000000000000E+000
-8.030721305131819E-002, 0.000000000000000E+000
-8.030721305131819E-002, 0.000000000000000E+000
-8.030721305131819E-002, 0.000000000000000E+000
-1.093193310824843E-001, 0.000000000000000E+000
    </PHI.1.2>
    <PHI.2.1 type="complex" size="9">
-1.093193310824842E-001, 0.000000000000000E+000
 8.030721305131817E-002, 0.000000000000000E+000
-8.030721305131817E-002, 0.000000000000000E+000
 8.030721305131816E-002, 0.000000000000000E+000
-1.093193310824842E-001, 0.000000000000000E+000
-8.030721305131820E-002, 0.000000000000000E+000
-8.030721305131816E-002, 0.000000000000000E+000
-8.030721305131820E-002, 0.000000000000000E+000
-1.093193310824842E-001, 0.000000000000000E+000
    </PHI.2.1>
    <PHI.2.2 type="complex" size="9">
 2.318234680748539E-001, 0.000000000000000E+000
 2.363352848976948E-002, 0.000000000000000E+000
-2.363352848976948E-002, 0.000000000000000E+000
 2.363352848976950E-002, 0.000000000000000E+000
 2.318234680748539E-001, 0.000000000000000E+000
-2.363352848976948E-002, 0.000000000000000E+000
-2.363352848976948E-002, 0.000000000000000E+000
-2.363352848976948E-002, 0.000000000000000E+000
 2.318234680748539E-001, 0.000000000000000E+000
    </PHI.2.2>
  </DYNAMICAL_MAT_.4>
  <FREQUENCIES_THZ_CMM1>
    <OMEGA.1 type="real" size="2" columns="2">
 2.016727880937754E+000  6.727080108658883E+001
    </OMEGA.1>
    <DISPLACEMENT.1 type="complex" size="6">
-5.195352920254788E-001, 0.000000000000000E+000
-6.475465555422860E-002, 0.000000000000000E+000
 4.547806364712504E-001, 0.000000000000000E+000
-5.397371229829250E-001, 0.000000000000000E+000
-6.727260308405685E-002, 0.000000000000000E+000
 4.724645198988681E-001, 0.000000000000000E+000
    </DISPLACEMENT.1>
    <OMEGA.2 type="real" size="2" columns="2">
 2.016727880937761E+000  6.727080108658907E+001
    </OMEGA.2>
    <DISPLACEMENT.2 type="complex" size="6">
 2.251816050733904E-001, 0.000000000000000E+000
 5.625215635933266E-001, 0.000000000000000E+000
 3.373399585199365E-001, 0.000000000000000E+000
 2.339376622464918E-001, 0.000000000000000E+000
 5.843948909919847E-001, 0.000000000000000E+000
 3.504572287454932E-001, 0.000000000000000E+000
    </DISPLACEMENT.2>
    <OMEGA.3 type="real" size="2" columns="2">
 6.494424287137338E+000  2.166306761171870E+002
    </OMEGA.3>
    <DISPLACEMENT.3 type="complex" size="6">
-1.416502544890942E-001, 0.000000000000000E+000
 1.416502544890939E-001, 0.000000000000000E+000
-1.416502544890942E-001, 0.000000000000000E+000
 5.597039742011021E-001, 0.000000000000000E+000
-5.597039742011023E-001, 0.000000000000000E+000
 5.597039742011024E-001, 0.000000000000000E+000
    </DISPLACEMENT.3>
    <OMEGA.4 type="real" size="2" columns="2">
 1.094086910563064E+001  3.649481103901101E+002
    </OMEGA.4>
    <DISPLACEMENT.4 type="complex" size="6">
 7.592589900408129E-001, 0.000000000000000E+000
 2.612664512412554E-001, 0.000000000000000E+000
-4.979925387995599E-001, 0.000000000000000E+000
-2.631884850914152E-001, 0.000000000000000E+000
-9.056504092720671E-002, 0.000000000000000E+000
 1.726234441642083E-001, 0.000000000000000E+000
    </DISPLACEMENT.4>
    <OMEGA.5 type="real" size="2" columns="2">
 1.094086910563065E+001  3.649481103901101E+002
    </OMEGA.5>
    <DISPLACEMENT.5 type="complex" size="6">
-1.366738703759941E-001, 0.000000000000000E+000
-7.258745086150576E-001, 0.000000000000000E+000
-5.892006382390640E-001, 0.000000000000000E+000
 4.737644119815386E-002, 0.000000000000000E+000
 2.516161346717843E-001, 0.000000000000000E+000
 2.042396934736305E-001, 0.000000000000000E+000
    </DISPLACEMENT.5>
    <OMEGA.6 type="real" size="2" columns="2">
 1.155167942029306E+001  3.853225493849169E+002
    </OMEGA.6>
    <DISPLACEMENT.6 type="complex" size="6">
-5.749672892512419E-001, 0.000000000000000E+000
 5.749672892512405E-001, 0.000000000000000E+000
-5.749672892512401E-001, 0.000000000000000E+000
-5.240180936201806E-002, 0.000000000000000E+000
 5.240180936201858E-002, 0.000000000000000E+000
-5.240180936201868E-002, 0.000000000000000E+000
    </DISPLACEMENT.6>
  </FREQUENCIES_THZ_CMM1>
</Root>
 
